{
    "Characteristics": [
        {
            "name": "About energy", 
            "vars": [
                {
                    "name": "ASSfb9c038c3a49_char_energy_pos"
                }, 
                {
                    "name": "ASSfb9c038c3a49_char_energy_neg"
                }
            ], 
            "id": 239
        }, 
        {
            "name": "About love", 
            "vars": [
                {
                    "name": "ASSfb9c038c3a49_char_love_pos"
                }, 
                {
                    "name": "ASSfb9c038c3a49_char_love_neg"
                }
            ], 
            "id": 240
        }, 
        {
            "name": "Overall Characteristic", 
            "vars": [
                {
                    "name": "ASSfb9c038c3a49_char_overallperf_pos"
                }, 
                {
                    "name": "ASSfb9c038c3a49_char_overallperf_neg"
                }
            ], 
            "id": 204
        }
    ], 
    "Explanatory": [], 
    "Performance": [
        {
            "name": "Overall performace", 
            "vars": [
                {
                    "name": "ASSfb9c038c3a49_perf_overallchar_1"
                }, 
                {
                    "name": "ASSfb9c038c3a49_perf_overallchar_2"
                }, 
                {
                    "name": "ASSfb9c038c3a49_perf_overallchar_3"
                }
            ], 
            "id": 205
        }
    ]
}